humantechsys/__init__.py
humantechsys/food.py
humantechsys-1.3.dist-info/METADATA
humantechsys-1.3.dist-info/WHEEL
humantechsys-1.3.dist-info/top_level.txt
humantechsys-1.3.dist-info/RECORD
